loyaleditor/__init__.py
loyaleditor/cli.py
loyaleditor/editor.py
loyal_editor-1.0.0.dist-info/LICENSE.txt
loyal_editor-1.0.0.dist-info/METADATA
loyal_editor-1.0.0.dist-info/WHEEL
loyal_editor-1.0.0.dist-info/entry_points.txt
loyal_editor-1.0.0.dist-info/top_level.txt
loyal_editor-1.0.0.dist-info/RECORD
