Metadata-Version: 2.1
Name: loyal-editor
Version: 1.0.0
Summary: Терминальный текстовый редактор с нумерацией строк
Author: Ваше имя
Classifier: Programming Language :: Python :: 3
Classifier: Operating System :: OS Independent
Requires-Python: >=3.6
License-File: LICENSE.txt
Requires-Dist: colorama
